./.env.example
./.gitignore
./.python-version
./PKG-INFO
./README.md
./client.py
./client_first_mcp.py
./pyproject.toml
./twilio_manager_client.py
./twilio_manager_client_sse.py
./twilio_manager_mcp.py
./twilio_manager_mcp_sse.py
./uv.lock
./.cursor/mcp.json.example
./api/async_twilio_api.py
./api/async_twilio_wrapper.py
./clients/client.py
./clients/client_sse.py
api/async_twilio_api.py
api/async_twilio_wrapper.py
twilio_manager_mcp-0.1.6.dist-info/METADATA
twilio_manager_mcp-0.1.6.dist-info/WHEEL
twilio_manager_mcp-0.1.6.dist-info/entry_points.txt
twilio_manager_mcp-0.1.6.dist-info/RECORD
