Metadata-Version: 2.4
Name: twilio-manager-mcp
Version: 0.1.6
Summary: Twilio Manager MCP connects Claude AI or any host to Twilio through the Model Context Protocol (MCP)
Project-URL: Homepage, https://github.com/errajibadr/twilio-manager-mcp
Project-URL: Bug Tracker, https://github.com/errajibadr/twilio-manager-mcp/issues
Author-email: Erraj Badr <errajibadr@gmail.com>
License: MIT
Classifier: License :: OSI Approved :: MIT License
Classifier: Operating System :: OS Independent
Classifier: Programming Language :: Python :: 3
Classifier: Topic :: Communications :: Telephony
Classifier: Topic :: Utilities
Requires-Python: >=3.12
Requires-Dist: aiohttp>=3.8.0
Requires-Dist: mcp[cli]>=1.4.1
Requires-Dist: python-dotenv>=1.0.0
Requires-Dist: twilio>=9.5.1
